dbautomodel/__init__.py
dbautomodel/module.py
dbautomodel-0.0.1.dist-info/LICENSE
dbautomodel-0.0.1.dist-info/METADATA
dbautomodel-0.0.1.dist-info/WHEEL
dbautomodel-0.0.1.dist-info/top_level.txt
dbautomodel-0.0.1.dist-info/RECORD
