Metadata-Version: 2.2
Name: dbautomodel
Version: 0.0.1
Summary: lib for auto model sql queries
Home-page: https://github.com/Myshica/dbautomodel
Author: Aero
Author-email: email@example.com
Classifier: License :: OSI Approved :: MIT License
Classifier: Operating System :: OS Independent
Requires-Python: >=3.12
License-File: LICENSE
Dynamic: author
Dynamic: author-email
Dynamic: classifier
Dynamic: description
Dynamic: description-content-type
Dynamic: home-page
Dynamic: requires-python
Dynamic: summary
